sbx_metadata/__init__.py
sbx_metadata/json_export.py
sbx_metadata/metadata_utils.py
sbx_metadata/metashare.py
sparv_sbx_metadata-1.0.1.dist-info/LICENSE
sparv_sbx_metadata-1.0.1.dist-info/METADATA
sparv_sbx_metadata-1.0.1.dist-info/WHEEL
sparv_sbx_metadata-1.0.1.dist-info/entry_points.txt
sparv_sbx_metadata-1.0.1.dist-info/top_level.txt
sparv_sbx_metadata-1.0.1.dist-info/RECORD
