Metadata-Version: 2.1
Name: sparv-sbx-metadata
Version: 1.0.1
Summary: Sparv plugin for SBX specific export of metadata
Home-page: https://github.com/spraakbanken/sparv-sbx-metadata/
Author: Språkbanken
Author-email: sb-info@svenska.gu.se
License: MIT
Requires-Python: >=3.6.2
License-File: LICENSE
Requires-Dist: langcodes[data] (>=2.1.0)
Requires-Dist: sparv-pipeline (>=5.0.1.dev0)
